termitty/__init__.py
termitty/core/__init__.py
termitty/core/config.py
termitty/core/exceptions.py
termitty/interactive/__init__.py
termitty/interactive/io_handler.py
termitty/interactive/key_codes.py
termitty/interactive/patterns.py
termitty/interactive/shell.py
termitty/parallel/__init__.py
termitty/parallel/executor.py
termitty/parallel/pool.py
termitty/parallel/results.py
termitty/parsers/__init__.py
termitty/recording/__init__.py
termitty/recording/formats.py
termitty/recording/player.py
termitty/recording/recorder.py
termitty/recording/storage.py
termitty/session/__init__.py
termitty/session/session.py
termitty/terminal/__init__.py
termitty/terminal/ansi_parser.py
termitty/terminal/screen_buffer.py
termitty/terminal/virtual_terminal.py
termitty/transport/__init__.py
termitty/transport/base.py
termitty/transport/paramiko_transport.py
termitty/utils/__init__.py
termitty-0.1.1.dist-info/licenses/LICENSE
termitty-0.1.1.dist-info/METADATA
termitty-0.1.1.dist-info/WHEEL
termitty-0.1.1.dist-info/top_level.txt
termitty-0.1.1.dist-info/RECORD
