Metadata-Version: 2.4
Name: termitty
Version: 0.1.1
Summary: A Selenium-inspired Python framework for terminal and SSH automation
Author-email: Deep <hellol@termitty.com>
License: MIT
Project-URL: Homepage, https://github.com/termitty/termitty
Project-URL: Bug Reports, https://github.com/termitty/termitty/issues
Project-URL: Source, https://github.com/termitty/termitty
Project-URL: Documentation, https://termitty.readthedocs.io
Keywords: ssh,terminal,automation,devops,remote execution
Classifier: Development Status :: 2 - Pre-Alpha
Classifier: Intended Audience :: Developers
Classifier: License :: OSI Approved :: MIT License
Classifier: Operating System :: OS Independent
Classifier: Programming Language :: Python :: 3.8
Classifier: Programming Language :: Python :: 3.9
Classifier: Programming Language :: Python :: 3.10
Classifier: Programming Language :: Python :: 3.11
Classifier: Programming Language :: Python :: 3.12
Classifier: Topic :: Software Development :: Libraries :: Python Modules
Classifier: Topic :: System :: Systems Administration
Classifier: Topic :: System :: Networking
Requires-Python: >=3.8
License-File: LICENSE
Requires-Dist: paramiko>=3.0.0
Requires-Dist: asyncssh>=2.14.0
Requires-Dist: pyte>=0.8.1
Requires-Dist: prompt_toolkit>=3.0.0
Requires-Dist: rich>=13.0.0
Provides-Extra: dev
Requires-Dist: pytest>=7.0.0; extra == "dev"
Requires-Dist: pytest-asyncio>=0.21.0; extra == "dev"
Requires-Dist: pytest-cov>=4.0.0; extra == "dev"
Requires-Dist: pytest-mock>=3.10.0; extra == "dev"
Requires-Dist: black>=23.0.0; extra == "dev"
Requires-Dist: isort>=5.12.0; extra == "dev"
Requires-Dist: flake8>=6.0.0; extra == "dev"
Requires-Dist: mypy>=1.0.0; extra == "dev"
Requires-Dist: pre-commit>=3.0.0; extra == "dev"
Requires-Dist: tox>=4.0.0; extra == "dev"
Provides-Extra: docs
Requires-Dist: sphinx>=6.0.0; extra == "docs"
Requires-Dist: sphinx-rtd-theme>=1.2.0; extra == "docs"
Requires-Dist: sphinx-autodoc-typehints>=1.22.0; extra == "docs"
Provides-Extra: ui
Requires-Dist: rich>=13.0.0; extra == "ui"
Dynamic: license-file
